torchtime/datasets/__init__.py
torchtime/datasets/data_io.py
torchtime/datasets/inditrain.py
torchtime/datasets/pandas.py
torchtime/datasets/timeseries.py
torchtime/datasets/ucruea.py
torchtime/datasets/utils.py
torchtime/io/__init__.py
torchtime/io/arff.py
torchtime/io/ts.py
torchtime/models/__init__.py
torchtime/models/_api.py
torchtime/models/inception.py
torchtime/models/tstmae.py
torchtime/transforms/__init__.py
torchtime/transforms/functional.py
torchtime/transforms/transforms.py
pytorchtime-0.1.2.dist-info/LICENSE
pytorchtime-0.1.2.dist-info/METADATA
pytorchtime-0.1.2.dist-info/WHEEL
pytorchtime-0.1.2.dist-info/top_level.txt
pytorchtime-0.1.2.dist-info/RECORD
