Metadata-Version: 2.1
Name: pytorchtime
Version: 0.1.2
Summary: A time series package for PyTorch
Author-email: Vincent Scharf <vincent.scharf@smail.inf.h-brs.de>
Project-URL: repository, https://github.com/VincentSch4rf/torchtime
Keywords: python,torchtime
Classifier: Environment :: Plugins
Classifier: Intended Audience :: Developers
Classifier: Intended Audience :: Science/Research
Classifier: License :: OSI Approved :: BSD License
Classifier: Operating System :: MacOS :: MacOS X
Classifier: Operating System :: Microsoft :: Windows
Classifier: Operating System :: POSIX
Classifier: Programming Language :: C++
Classifier: Programming Language :: Python :: 3.8
Classifier: Programming Language :: Python :: 3.9
Classifier: Programming Language :: Python :: 3.10
Classifier: Programming Language :: Python :: 3.11
Classifier: Programming Language :: Python :: 3.12
Classifier: Programming Language :: Python :: Implementation :: CPython
Classifier: Topic :: Scientific/Engineering :: Artificial Intelligence
License-File: LICENSE
Requires-Dist: torch ==2.4.*
Requires-Dist: pytorch-lightning ==2.4.*
Requires-Dist: requests
Requires-Dist: typing-extensions
Requires-Dist: numpy
Requires-Dist: tqdm
Requires-Dist: pandas
Provides-Extra: test
Requires-Dist: pytest ==7.4.* ; extra == 'test'
Requires-Dist: pytest-mock ==3.10.* ; extra == 'test'
